simple_salesforce/__init__.py
simple_salesforce/__version__.py
simple_salesforce/api.py
simple_salesforce/bulk.py
simple_salesforce/exceptions.py
simple_salesforce/login.py
simple_salesforce/util.py
simple_salesforce_pybaitz-0.74.2.dist-info/LICENSE.txt
simple_salesforce_pybaitz-0.74.2.dist-info/METADATA
simple_salesforce_pybaitz-0.74.2.dist-info/WHEEL
simple_salesforce_pybaitz-0.74.2.dist-info/top_level.txt
simple_salesforce_pybaitz-0.74.2.dist-info/RECORD
