Metadata-Version: 2.1
Name: simple-salesforce-pybaitz
Version: 0.74.2
Summary: A basic Salesforce.com REST API client.
Home-page: https://github.com/simple-salesforce/simple-salesforce
Author: Nick Catalano
Author-email: nickcatal@gmail.com
Maintainer: Demian Brecht
Maintainer-email: demianbrecht@gmail.com
License: Apache 2.0
Keywords: python salesforce salesforce.com
Platform: UNKNOWN
Classifier: Development Status :: 4 - Beta
Classifier: License :: OSI Approved :: Apache Software License
Classifier: Intended Audience :: Developers
Classifier: Intended Audience :: System Administrators
Classifier: Operating System :: OS Independent
Classifier: Topic :: Internet :: WWW/HTTP
Classifier: Programming Language :: Python :: 2.6
Classifier: Programming Language :: Python :: 2.7
Classifier: Programming Language :: Python :: 3.3
Classifier: Programming Language :: Python :: 3.4
Classifier: Programming Language :: Python :: 3.5
Classifier: Programming Language :: Python :: 3.6
Classifier: Programming Language :: Python :: Implementation :: PyPy
Requires-Dist: requests[security]
